help_me_bob/__init__.py
help_me_bob/__main__.py
help_me_bob/models.py
help_me_bob/services.py
help_me_bob/data/clear.csv
help_me_bob-0.1.2.dist-info/METADATA
help_me_bob-0.1.2.dist-info/WHEEL
help_me_bob-0.1.2.dist-info/entry_points.txt
help_me_bob-0.1.2.dist-info/RECORD
