Metadata-Version: 2.4
Name: help-me-bob
Version: 0.1.2
Summary: Get random Bob Dylan lyrics whenever you need them
Project-URL: Homepage, https://github.com/rafasacaan/help-me-bob
Author-email: rafa sacaan <rafasacaan@gmail.com>
Classifier: License :: OSI Approved :: MIT License
Classifier: Operating System :: OS Independent
Classifier: Programming Language :: Python :: 3
Requires-Python: >=3.9
Requires-Dist: pandas>=2.2.3
Requires-Dist: pytest-cov>=6.0.0
Requires-Dist: pytest>=8.3.4
